setup.py
datadiff/__init__.py
datadiff/tools.py
datadiff/version.py
gnulnx_datadiff.egg-info/PKG-INFO
gnulnx_datadiff.egg-info/SOURCES.txt
gnulnx_datadiff.egg-info/dependency_links.txt
gnulnx_datadiff.egg-info/pbr.json
gnulnx_datadiff.egg-info/top_level.txt