Metadata-Version: 1.1
Name: gnulnx-datadiff
Version: 1.1.6
Summary: DataDiff is a library to provide human-readable diffs of python data structures.
Home-page: http://sourceforge.net/projects/datadiff/
Author: Dave Brondsema
Author-email: dave@brondsema.net
License: Apache License
Keywords: data,diff
Platform: UNKNOWN
Classifier: Programming Language :: Python
Classifier: Programming Language :: Python :: 3
Classifier: Development Status :: 4 - Beta
Classifier: Intended Audience :: Developers
Classifier: License :: OSI Approved :: Apache Software License
Classifier: Operating System :: OS Independent
Classifier: Topic :: Software Development :: Libraries :: Python Modules
